jumpstarter_driver_raspberrypi/__init__.py
jumpstarter_driver_raspberrypi/client.py
jumpstarter_driver_raspberrypi/driver.py
jumpstarter_driver_raspberrypi/driver_test.py
jumpstarter_driver_raspberrypi/py.typed
jumpstarter_driver_raspberrypi-0.6.0.dist-info/METADATA
jumpstarter_driver_raspberrypi-0.6.0.dist-info/WHEEL
jumpstarter_driver_raspberrypi-0.6.0.dist-info/entry_points.txt
jumpstarter_driver_raspberrypi-0.6.0.dist-info/RECORD
