Metadata-Version: 2.4
Name: jumpstarter-driver-raspberrypi
Version: 0.6.0
Project-URL: Homepage, https://jumpstarter.dev
Project-URL: source_archive, https://github.com/jumpstarter-dev/repo/archive/c2927a2abac82d224c7bd28f9ed83c57b5222e65.zip
Author-email: Miguel Angel Ajo Pelayo <majopela@redhat.com>, Nick Cao <ncao@redhat.com>, Kirk Brauer <kbrauer@hatci.com>
License-Expression: Apache-2.0
Requires-Python: >=3.11
Requires-Dist: gpiozero>=2.0.1
Requires-Dist: jumpstarter==0.6.0
